tree_sitter_parsers/__init__.py
tree_sitter_parsers/ast_parser.py
tree_sitter_parsers-0.0.7.dist-info/METADATA
tree_sitter_parsers-0.0.7.dist-info/WHEEL
tree_sitter_parsers-0.0.7.dist-info/top_level.txt
tree_sitter_parsers-0.0.7.dist-info/RECORD
